mj_odd_or_even/__init__.py
mj_odd_or_even-0.1.0.dist-info/licenses/LICENSE
mj_odd_or_even-0.1.0.dist-info/METADATA
mj_odd_or_even-0.1.0.dist-info/WHEEL
mj_odd_or_even-0.1.0.dist-info/top_level.txt
mj_odd_or_even-0.1.0.dist-info/RECORD
