Metadata-Version: 2.4
Name: mj_odd_or_even
Version: 0.1.0
Summary: A simple library to check odd and even numbers.
Author-email: Maria Jose <4mariajo@gmail.com>
License: MIT License
Keywords: odd,even,numbers
Requires-Python: >=3.7
License-File: LICENSE
Dynamic: license-file
